pyquiet/__init__.py
pyquiet/QiParser/QiParser.py
pyquiet/QiParser/__init__.py
pyquiet/antlr/QuietLexer.py
pyquiet/antlr/QuietParser.py
pyquiet/antlr/QuietParserListener.py
pyquiet/antlr/QuietParserVisitor.py
pyquiet/antlr/__init__.py
pyquiet/qir/__init__.py
pyquiet/qir/qi_prog.py
pyquiet/qir/qcode/__init__.py
pyquiet/qir/qcode/section.py
pyquiet/qir/qentry/__init__.py
pyquiet/qir/qentry/section.py
pyquiet/qir/qfile/__init__.py
pyquiet/qir/qfile/file.py
pyquiet/qir/qfile/section.py
pyquiet/qir/qfunction/__init__.py
pyquiet/qir/qfunction/function.py
pyquiet/qir/qgate/__init__.py
pyquiet/qir/qgate/gate.py
pyquiet/qir/qgate/section.py
pyquiet/qir/qinstructions/__init__.py
pyquiet/qir/qinstructions/func_call.py
pyquiet/qir/qinstructions/insn_base.py
pyquiet/qir/qinstructions/label.py
pyquiet/qir/qinstructions/quantum_op.py
pyquiet/qir/qinstructions/var_decl.py
pyquiet/qir/qinstructions/modules_instruction/__init__.py
pyquiet/qir/qinstructions/modules_instruction/classical_insn_base.py
pyquiet/qir/qinstructions/modules_instruction/ct/__init__.py
pyquiet/qir/qinstructions/modules_instruction/ct/instructions.py
pyquiet/qir/qinstructions/modules_instruction/fm/__init__.py
pyquiet/qir/qinstructions/modules_instruction/fm/instructions.py
pyquiet/qir/qinstructions/modules_instruction/im/__init__.py
pyquiet/qir/qinstructions/modules_instruction/im/instructions.py
pyquiet/qir/qinstructions/modules_instruction/pm/__init__.py
pyquiet/qir/qinstructions/modules_instruction/pm/cus_pm_insn.py
pyquiet/qir/qinstructions/modules_instruction/pm/instructions.py
pyquiet/qir/qinstructions/modules_instruction/std/__init__.py
pyquiet/qir/qinstructions/modules_instruction/std/control_words.py
pyquiet/qir/qinstructions/modules_instruction/std/instructions.py
pyquiet/qir/qinstructions/modules_instruction/tm/__init__.py
pyquiet/qir/qinstructions/modules_instruction/tm/instructions.py
pyquiet/qir/qlayout/__init__.py
pyquiet/qir/qlayout/interface.py
pyquiet/qir/qlayout/section.py
pyquiet-0.1.0.dist-info/METADATA
pyquiet-0.1.0.dist-info/WHEEL
pyquiet-0.1.0.dist-info/top_level.txt
pyquiet-0.1.0.dist-info/RECORD
