Metadata-Version: 2.1
Name: pyquiet
Version: 0.1.0
Summary: A Python Parser for the Quiet Quantum Instruction Set
Home-page: https://gitee.com/hpcl_quanta/quiet-parser.git
Author: Yuzhen Zheng, Zhengdong Tang, Xiang Fu
Author-email: gtaifu@gmail.com
Project-URL: Bug Tracker, https://gitee.com/hpcl_quanta/quiet-parser/issues
Classifier: Programming Language :: Python :: 3 :: Only
Classifier: License :: OSI Approved :: Apache Software License
Classifier: Operating System :: OS Independent
Requires-Python: >=3.7
Requires-Dist: antlr4-python3-runtime (==4.13.0)
Requires-Dist: numpy
